{"cameraMode":{"drawMode":0,"name":"Shaded","section":"Shading Mode"},"sceneLighting":false,"audioPlay":false,"sceneViewState":{"showFog":true,"showMaterialUpdate":false,"showSkybox":false,"showFlares":true,"showImageEffects":true,"showParticleSystems":true},"in2DMode":false,"pivot":{"x":-0.06025099754333496,"y":18.56622314453125,"z":4.240996837615967},"rotation":{"x":-0.2890678942203522,"y":-0.11731255799531937,"z":0.03577373921871185,"w":-0.9496285915374756},"size":10.464463233947754,"orthographic":false}